MANIFEST.in
README.md
setup.py
reeds_shepp/reeds_shepp.cpp
reeds_shepp/reeds_shepp.pyx
reeds_shepp.egg-info/PKG-INFO
reeds_shepp.egg-info/SOURCES.txt
reeds_shepp.egg-info/dependency_links.txt
reeds_shepp.egg-info/top_level.txt
reeds_shepp/include/reeds_shepp.h
reeds_shepp/src/reeds_shepp.cpp