Metadata-Version: 1.1
Name: reeds-shepp
Version: 1.0.7
Summary: Code to calculate analytic Reeds Shepp path
Home-page: https://github.com/liespace/pyReedsShepp
Author: Gabel Liemann
Author-email: troubleli233@gmail.com
License: MIT
Platform: UNKNOWN
Classifier: Programming Language :: Python :: 2
Classifier: License :: OSI Approved :: MIT License
Classifier: Operating System :: POSIX :: Linux
Classifier: Topic :: Scientific/Engineering :: Mathematics
